{
  "main": {
    "id": "da42f53e26dde3d8",
    "type": "split",
    "children": [
      {
        "id": "7186c7eafe1f52d5",
        "type": "tabs",
        "children": [
          {
            "id": "144b7d2d2d1a7d11",
            "type": "leaf",
            "state": {
              "type": "empty",
              "state": {}
            }
          }
        ]
      }
    ],
    "direction": "vertical"
  },
  "left": {
    "id": "d71d91f5db33e129",
    "type": "split",
    "children": [
      {
        "id": "41e0d4bd26665ac5",
        "type": "tabs",
        "dimension": 72.25,
        "children": [
          {
            "id": "b5a872acba62dc41",
            "type": "leaf",
            "state": {
              "type": "file-explorer",
              "state": {
                "sortOrder": "alphabetical"
              }
            }
          },
          {
            "id": "6e7e3603c1b3de6d",
            "type": "leaf",
            "state": {
              "type": "search",
              "state": {
                "query": "",
                "matchingCase": false,
                "explainSearch": false,
                "collapseAll": false,
                "extraContext": false,
                "sortOrder": "alphabetical"
              }
            }
          },
          {
            "id": "254230380ce8c8f6",
            "type": "leaf",
            "state": {
              "type": "bookmarks",
              "state": {}
            }
          },
          {
            "id": "adeaa48921a07d37",
            "type": "leaf",
            "state": {
              "type": "recent-files",
              "state": {}
            }
          }
        ]
      },
      {
        "id": "e180528521c779fa",
        "type": "tabs",
        "dimension": 27.750000000000004,
        "children": [
          {
            "id": "d4c1dad0b2eb993d",
            "type": "leaf",
            "state": {
              "type": "graph",
              "state": {}
            }
          }
        ]
      }
    ],
    "direction": "horizontal",
    "width": 256.001522064209
  },
  "right": {
    "id": "f42982c75c503ce7",
    "type": "split",
    "children": [
      {
        "id": "6ae10e012348baf8",
        "type": "tabs",
        "children": [
          {
            "id": "8a18041c6bb61750",
            "type": "leaf",
            "state": {
              "type": "backlink",
              "state": {
                "collapseAll": false,
                "extraContext": false,
                "sortOrder": "alphabetical",
                "showSearch": false,
                "searchQuery": "",
                "backlinkCollapsed": false,
                "unlinkedCollapsed": true
              }
            }
          },
          {
            "id": "3fe65feb6fe27824",
            "type": "leaf",
            "state": {
              "type": "outgoing-link",
              "state": {
                "linksCollapsed": false,
                "unlinkedCollapsed": true
              }
            }
          },
          {
            "id": "d24f7da70e2f8392",
            "type": "leaf",
            "state": {
              "type": "tag",
              "state": {
                "sortOrder": "frequency",
                "useHierarchy": true
              }
            }
          },
          {
            "id": "4c5b6fa0945a52f0",
            "type": "leaf",
            "state": {
              "type": "all-properties",
              "state": {
                "sortOrder": "frequency",
                "showSearch": false,
                "searchQuery": ""
              }
            }
          },
          {
            "id": "fbafc402b6eaf840",
            "type": "leaf",
            "state": {
              "type": "outline",
              "state": {}
            }
          },
          {
            "id": "070007af34b1edb5",
            "type": "leaf",
            "state": {
              "type": "advanced-tables-toolbar",
              "state": {}
            }
          }
        ],
        "currentTab": 5
      }
    ],
    "direction": "horizontal",
    "width": 200,
    "collapsed": true
  },
  "left-ribbon": {
    "hiddenItems": {
      "daily-notes:Open today's daily note": false,
      "switcher:Open quick switcher": true,
      "canvas:Create new canvas": true,
      "templates:Insert template": true,
      "command-palette:Open command palette": false,
      "graph:Open graph view": false,
      "workspaces:Manage workspace layouts": true,
      "obsidian-focus-mode:Toggle Focus Mode (Shift + Click to show active pane only)": false,
      "obsidian-projects:Open projects": false,
      "table-editor-obsidian:Advanced Tables Toolbar": false
    }
  },
  "active": "144b7d2d2d1a7d11",
  "lastOpenFiles": []
}
